ati_langchain/__init__.py
ati_langchain/callbacks.py
ati_langchain/instrumentor.py
ati_langchain/version.py
ati_integrations_langchain-0.1.1.dist-info/METADATA
ati_integrations_langchain-0.1.1.dist-info/WHEEL
ati_integrations_langchain-0.1.1.dist-info/RECORD
